Metadata-Version: 1.0
Name: GML-distributions
Version: 0.1
Summary: Gaussian and Binomial distributions
Home-page: UNKNOWN
Author: Siqi Huang
Author-email: siqi.huang@boehringer-ingelheim.com
License: UNKNOWN
Platform: UNKNOWN
